{
    "subjects": [
        {
            "name": "Шахматы",
            "time": "3 года",
            "Стоимость": 4500,
            "Сова": "Вы полюбите шахматы, и вам этого будет нехватать всегда",
            "Цели": [
                "Привить интерес к шахматам",
                "Получить удовольствие от процесса игры, от факта победы в партии, от спасения",
                "Научиться анализировать свои и чужие ошибки, учиться на них с помощью GM мирового уровня",
                "Получить удовольствие от процесса игры, от факта победы в партии, от спасения"
            ]
        },
        {
            "name": "Создание игр",
            "time": "2 года",
            "Стоимость": 10000,
            "Сова": "Вы полюбите игры, и будете видеть все ошибки в чужой игре",
            "Цели": [
                "Привить интерес к играм",
                "Получить удовольствие от процесса игры, от факта победы, от спасения, потраченного времени",
                "Научиться анализировать свои и чужие ошибки",
                "Получить удовольствие от процесса игры, от факта победы, от спасения, потраченного времени"
            ]
        },
        {
            "name": "Робототехника",
            "time": "4 года",
            "Стоимость": 8000,
            "Сова": "Вы полюбите роботов, даже сами сможете собрать себе маленького помощника",
            "Цели": [
                "Привить интерес к робототехнике",
                "Получить удовольствие от процесса сборки, проектирования роботов",
                "Научиться анализировать свои и чужие ошибки",
                "Участвовать и побеждать в соревнованиях всей России"
            ]
        },
        {
            "name": "Web-разработка",
            "time": "2 года",
            "Стоимость": 5000,
            "Сова": "Вы сможете сделать себе самому сайт, познакомитесь с HTML, CSS,JS и много чем другим",
            "Цели": [
                "Привить интерес к верстанию",
                "Получить удовольствие от процесса разработки, редактирования страниц",
                "Научиться писать на JavaScript с полным пониманием, что происходит",
                "Участвовать и побеждать в хакатонах всего мира!"
            ]
        },
        {
            "name": "Мультимедиа",
            "time": "3 года",
            "Стоимость": 7000,
            "Сова": "Вся основная (и немного больше) информация для создания популярных видеороликов. Ещё чуть-чуть и можно получить бриллиантовую кнопку",
            "Цели": [
                "Привить интерес к созаднию видеороликов",
                "Получить удовольствие от процесса разработки, редактирования страниц",
                "Научиться анализировать свои и чужие ошибки",
                "Захватить YouTube и много других площадок!"
            ]
        },
        {
            "name": "Мультимедиа",
            "time": "3 года",
            "Стоимость": 7000,
            "Сова": "Вся основная (и немного больше) информация для создания популярных видеороликов. Ещё чуть-чуть и можно получить бриллиантовую кнопку",
            "Цели": [
                "Привить интерес к созаднию видеороликов",
                "Получить удовольствие от процесса разработки, редактирования страниц",
                "Научиться анализировать свои и чужие ошибки",
                "Захватить YouTube и много других площадок!"
            ]
        },
        {
            "name": "Мультимедиа",
            "time": "3 года",
            "Стоимость": 7000,
            "Сова": "Вся основная (и немного больше) информация для создания популярных видеороликов. Ещё чуть-чуть и можно получить бриллиантовую кнопку",
            "Цели": [
                "Привить интерес к созаднию видеороликов",
                "Получить удовольствие от процесса разработки, редактирования страниц",
                "Научиться анализировать свои и чужие ошибки",
                "Захватить YouTube и много других площадок!"
            ]
        },
        {
            "name": "Мультимедиа",
            "time": "3 года",
            "Стоимость": 7000,
            "Сова": "Вся основная (и немного больше) информация для создания популярных видеороликов. Ещё чуть-чуть и можно получить бриллиантовую кнопку",
            "Цели": [
                "Привить интерес к созаднию видеороликов",
                "Получить удовольствие от процесса разработки, редактирования страниц",
                "Научиться анализировать свои и чужие ошибки",
                "Захватить YouTube и много других площадок!"
            ]
        },
        {
            "name": "Мультимедиа",
            "time": "3 года",
            "Стоимость": 7000,
            "Сова": "Вся основная (и немного больше) информация для создания популярных видеороликов. Ещё чуть-чуть и можно получить бриллиантовую кнопку",
            "Цели": [
                "Привить интерес к созаднию видеороликов",
                "Получить удовольствие от процесса разработки, редактирования страниц",
                "Научиться анализировать свои и чужие ошибки",
                "Захватить YouTube и много других площадок!"
            ]
        },
        {
            "name": "Мультимедиа",
            "time": "3 года",
            "Стоимость": 7000,
            "Сова": "Вся основная (и немного больше) информация для создания популярных видеороликов. Ещё чуть-чуть и можно получить бриллиантовую кнопку",
            "Цели": [
                "Привить интерес к созаднию видеороликов",
                "Получить удовольствие от процесса разработки, редактирования страниц",
                "Научиться анализировать свои и чужие ошибки",
                "Захватить YouTube и много других площадок!"
            ]
        },
        {
            "name": "Мультимедиа",
            "time": "3 года",
            "Стоимость": 7000,
            "Сова": "Вся основная (и немного больше) информация для создания популярных видеороликов. Ещё чуть-чуть и можно получить бриллиантовую кнопку",
            "Цели": [
                "Привить интерес к созаднию видеороликов",
                "Получить удовольствие от процесса разработки, редактирования страниц",
                "Научиться анализировать свои и чужие ошибки",
                "Захватить YouTube и много других площадок!"
            ]
        },
        {
            "name": "Мультимедиа",
            "time": "3 года",
            "Стоимость": 7000,
            "Сова": "Вся основная (и немного больше) информация для создания популярных видеороликов. Ещё чуть-чуть и можно получить бриллиантовую кнопку",
            "Цели": [
                "Привить интерес к созаднию видеороликов",
                "Получить удовольствие от процесса разработки, редактирования страниц",
                "Научиться анализировать свои и чужие ошибки",
                "Захватить YouTube и много других площадок!"
            ]
        },
        {
            "name": "Мультимедиа",
            "time": "3 года",
            "Стоимость": 7000,
            "Сова": "Вся основная (и немного больше) информация для создания популярных видеороликов. Ещё чуть-чуть и можно получить бриллиантовую кнопку",
            "Цели": [
                "Привить интерес к созаднию видеороликов",
                "Получить удовольствие от процесса разработки, редактирования страниц",
                "Научиться анализировать свои и чужие ошибки",
                "Захватить YouTube и много других площадок!"
            ]
        },
        {
            "name": "Мультимедиа",
            "time": "3 года",
            "Стоимость": 7000,
            "Сова": "Вся основная (и немного больше) информация для создания популярных видеороликов. Ещё чуть-чуть и можно получить бриллиантовую кнопку",
            "Цели": [
                "Привить интерес к созаднию видеороликов",
                "Получить удовольствие от процесса разработки, редактирования страниц",
                "Научиться анализировать свои и чужие ошибки",
                "Захватить YouTube и много других площадок!"
            ]
        }
    ]
}